src/__init__.py
src/audio_gatedcnnarch.py
src/cgraphviz.py
src/ckpt_hookers.py
src/dataloader.py
src/fishers_multiclass.py
src/hidrometer_consumption.py
src/model.py
src/modelsaver.py
src/pre_processing.py
src/sgdfilters.py
src/spect.py
src/template.py
src/tfhelper.py
audiomodels-0.1.dev3.dist-info/LICENSE
audiomodels-0.1.dev3.dist-info/METADATA
audiomodels-0.1.dev3.dist-info/WHEEL
audiomodels-0.1.dev3.dist-info/top_level.txt
audiomodels-0.1.dev3.dist-info/RECORD
